cartouche/__init__.py
cartouche/apps.py
cartouche/compiler.py
cartouche/middleware.py
cartouche/py.typed
cartouche/tracking.py
cartouche/urls.py
cartouche/views.py
cartouche/static/cartouche/editor.css
cartouche/static/cartouche/editor.js
django_cartouche-0.3.2.dist-info/METADATA
django_cartouche-0.3.2.dist-info/WHEEL
django_cartouche-0.3.2.dist-info/licenses/LICENSE
django_cartouche-0.3.2.dist-info/RECORD
