Metadata-Version: 2.4
Name: django-cartouche
Version: 0.3.2
Summary: Inline translation string editing for Django
Project-URL: Homepage, https://github.com/rnegron/django-cartouche
Project-URL: Documentation, https://django-cartouche.readthedocs.io
Project-URL: Repository, https://github.com/rnegron/django-cartouche
Project-URL: Changelog, https://github.com/rnegron/django-cartouche/blob/main/CHANGELOG.md
Author-email: Raúl Negrón-Otero <raul.esteban.negron@gmail.com>
License-Expression: MIT
License-File: LICENSE
Keywords: django,gettext,i18n,po,translation
Classifier: Development Status :: 4 - Beta
Classifier: Framework :: Django
Classifier: Framework :: Django :: 4.2
Classifier: Framework :: Django :: 5.0
Classifier: Framework :: Django :: 5.1
Classifier: Intended Audience :: Developers
Classifier: License :: OSI Approved :: MIT License
Classifier: Programming Language :: Python :: 3
Classifier: Programming Language :: Python :: 3.10
Classifier: Programming Language :: Python :: 3.11
Classifier: Programming Language :: Python :: 3.12
Classifier: Programming Language :: Python :: 3.13
Classifier: Topic :: Software Development :: Internationalization
Requires-Python: >=3.10
Requires-Dist: django>=4.2
Requires-Dist: polib>=1.2
